awaitless/__init__.py
awaitless-1.0.0.dist-info/LICENSE
awaitless-1.0.0.dist-info/METADATA
awaitless-1.0.0.dist-info/WHEEL
awaitless-1.0.0.dist-info/top_level.txt
awaitless-1.0.0.dist-info/RECORD
