Metadata-Version: 2.1
Name: awaitless
Version: 1.0.0
Summary: Teach async and interactive ipython sessions how to get along
Author-email: Graeme Smecher <gsmecher@t0.technology>
Project-URL: homepage, https://github.com/gsmecher/awaitless
Project-URL: repository, https://github.com/gsmecher/awaitless
License-File: LICENSE
Requires-Dist: aiohttp
Requires-Dist: IPython
Requires-Dist: pytest
